{
    "tournament_url_extension": "/us-open/2025/atp-men/",
    "date": "2025-08-21",
    "players_gender": "MEN",
    "player_1_url_extension": "/player/gigante-f720d/",
    "player_2_url_extension": "/player/wong-d3ead/",
    "player_1_odds": 2.17,
    "player_2_odds": 1.65,
    "score": "",
    "match_id": "b48378d57661f16ffee39ba77cf53f11",
    "round": "UNKNOWN",
    "player_1_elo": 2246.5196075159197,
    "player_2_elo": 2142.300824712463,
    "player_1_elo_on_surface": 2246.5196075159197,
    "player_2_elo_on_surface": 2142.300824712463,
    "atp_ranking_player_1": 131,
    "atp_points_player_1": 486.0,
    "atp_ranking_player_2": 174,
    "atp_points_player_2": 315.0,
    "player_1_id": "18c3b9fec235de86abe635d9e4a9c595",
    "player_2_id": "47b7d3678b6d1f043d6c458b9fe1d617",
    "tournament_id": "32f2f30d315c019e55af5669707a79bb",
    "surface": "Hard"
}