{
    "tournament_url_extension": "/monterrey/2025/wta-women/",
    "date": "2025-08-22",
    "players_gender": "WOMAN",
    "player_1_url_extension": "/player/shnaider-51347/",
    "player_2_url_extension": "/player/mertens-f8826/",
    "player_1_odds": 2.39,
    "player_2_odds": 1.56,
    "score": "",
    "match_id": "a7d73fca6f8497ffafc918017a33b064",
    "round": "UNKNOWN",
    "player_1_elo": 2397.727845260505,
    "player_2_elo": 2476.7203043784957,
    "player_1_elo_on_surface": 2397.727845260505,
    "player_2_elo_on_surface": 2476.7203043784957,
    "atp_ranking_player_1": 22,
    "atp_points_player_1": 2036.0,
    "atp_ranking_player_2": 21,
    "atp_points_player_2": 2051.0,
    "player_1_id": "fdc22aa0216e609a736a2e2d863534f1",
    "player_2_id": "e3d5d711aeb7d225b6a159ad1e1f2c90",
    "tournament_id": "477ef4d51726a7c001508d41c01222f1",
    "surface": "Hard"
}